{
  "openapi": "3.0.3",
  "info": {
    "title": "Swagger Petstore - OpenAPI 3.0",
    "description": "This is a sample Pet Store Server based on the OpenAPI 3.0 specification.  You can find out more about\nSwagger at [https://swagger.io](https://swagger.io). In the third iteration of the pet store, we've switched to the design first approach!\nYou can now help us improve the API whether it's by making changes to the definition itself or to the code.\nThat way, with time, we can improve the API in general, and expose some of the new features in OAS3.\n\n_If you're looking for the Swagger 2.0/OAS 2.0 version of Petstore, then click [here](https://editor.swagger.io/?url=https://petstore.swagger.io/v2/swagger.yaml). Alternatively, you can load via the `Edit > Load Petstore OAS 2.0` menu option!_\n\nSome useful links:\n- [The Pet Store repository](https://github.com/swagger-api/swagger-petstore)\n- [The source API definition for the Pet Store](https://github.com/swagger-api/swagger-petstore/blob/master/src/main/resources/openapi.yaml)",
    "termsOfService": "http://swagger.io/terms/",
    "contact": {
      "email": "apiteam@swagger.io"
    },
    "license": {
      "name": "Apache 2.0",
      "url": "http://www.apache.org/licenses/LICENSE-2.0.html"
    },
    "version": "1.0.11"
  },
  "externalDocs": {
    "description": "Find out more about Swagger",
    "url": "http://swagger.io"
  },
  "servers": [
    {
      "url": "https://petstore3.swagger.io/api/v3"
    }
  ],
  "tags": [
    {
      "name": "user",
      "description": "UserService"
    },
    {
      "name": "applicant",
      "description": "ApplicantService"
    },
    {
      "name": "manager",
      "description": "ManagerService"
    },
    {
      "name": "document",
      "description": "DocumentsService"
    },
    {
      "name": "admin",
      "description": "AdminService"
    },
    {
      "name": "notification",
      "description": "NotificationService"
    },
    {
      "name": "dictionary",
      "description": "DictionaryService"
    }
  ],
  "paths": {
    "/manager/register": {
      "post": {
        "tags": [
          "manager"
        ],
        "summary": "Register manager (only for admin)",
        "operationId": "RegisterManager",
        "requestBody": {
          "required": true,
          "content": {
            "application/json": {
              "schema": {
                "properties": {
                  "email": {
                    "type": "string"
                  },
                  "username": {
                    "type": "string"
                  },
                  "password": {
                    "type": "string"
                  },
                  "facultyId": {
                    "type": "string",
                    "format": "uuid"
                  }
                }
              }
            }
          }
        },
        "responses": {
          "200": {
            "description": "successful operation"
          }
        }
      }
    },
    "/manager/{applicationId}": {
      "patch": {
        "tags": [
          "manager"
        ],
        "summary": "Change application status by ID",
        "operationId": "ChangeApplicationStatus",
        "parameters": [
          {
            "name": "applicationId",
            "in": "path",
            "required": true,
            "schema": {
              "type": "string",
              "format": "uuid"
            }
          }
        ],
        "requestBody": {
          "required": true,
          "content": {
            "application/json": {
              "schema": {
                "$ref": "#/components/schemas/ApplicationStatus"
              }
            }
          }
        },
        "responses": {
          "200": {
            "description": "successful operation",
            "content": {
              "application/json": {
                "schema": {
                  "$ref": "#/components/schemas/ApplicationResponse"
                }
              }
            }
          }
        },
        "security": [
          {
            "bearerAuth": []
          }
        ]
      }
    },
    "/dictionary/import": {
      "post": {
        "tags": [
          "dictionary"
        ],
        "summary": "Import data from outer service (only admin)",
        "responses": {
          "200": {
            "description": "succesful operation"
          }
        }
      }
    },
    "/api/dictionary/education_levels": {
      "get": {
        "tags": [
          "dictionary"
        ],
        "summary": "Get a list of education levels",
        "responses": {
          "200": {
            "description": "Education levels list retrieved",
            "content": {
              "text/plain": {
                "schema": {
                  "type": "array",
                  "items": {
                    "$ref": "#/components/schemas/EducationLevelModel"
                  }
                }
              },
              "application/json": {
                "schema": {
                  "type": "array",
                  "items": {
                    "$ref": "#/components/schemas/EducationLevelModel"
                  }
                }
              },
              "text/json": {
                "schema": {
                  "type": "array",
                  "items": {
                    "$ref": "#/components/schemas/EducationLevelModel"
                  }
                }
              }
            }
          },
          "400": {
            "description": "Bad Request"
          },
          "401": {
            "description": "Unauthorized"
          },
          "403": {
            "description": "Forbidden"
          },
          "404": {
            "description": "Not Found"
          },
          "500": {
            "description": "InternalServerError",
            "content": {
              "application/json": {
                "schema": {
                  "$ref": "#/components/schemas/ResponseModel"
                }
              }
            }
          }
        },
        "security": [
          {
            "bearerAuth": []
          }
        ]
      }
    },
    "/api/dictionary/document_types": {
      "get": {
        "tags": [
          "dictionary"
        ],
        "summary": "Get a list of education document types",
        "responses": {
          "200": {
            "description": "Education document types list retrieved",
            "content": {
              "text/plain": {
                "schema": {
                  "type": "array",
                  "items": {
                    "$ref": "#/components/schemas/EducationDocumentTypeModel"
                  }
                }
              },
              "application/json": {
                "schema": {
                  "type": "array",
                  "items": {
                    "$ref": "#/components/schemas/EducationDocumentTypeModel"
                  }
                }
              },
              "text/json": {
                "schema": {
                  "type": "array",
                  "items": {
                    "$ref": "#/components/schemas/EducationDocumentTypeModel"
                  }
                }
              }
            }
          },
          "400": {
            "description": "Bad Request"
          },
          "401": {
            "description": "Unauthorized"
          },
          "403": {
            "description": "Forbidden"
          },
          "404": {
            "description": "Not Found"
          },
          "500": {
            "description": "InternalServerError",
            "content": {
              "application/json": {
                "schema": {
                  "$ref": "#/components/schemas/ResponseModel"
                }
              }
            }
          }
        },
        "security": [
          {
            "bearerAuth": []
          }
        ]
      }
    },
    "/api/dictionary/faculties": {
      "get": {
        "tags": [
          "dictionary"
        ],
        "summary": "Get a list of faculties",
        "responses": {
          "200": {
            "description": "Faculties list retrieved",
            "content": {
              "text/plain": {
                "schema": {
                  "type": "array",
                  "items": {
                    "$ref": "#/components/schemas/FacultyModel"
                  }
                }
              },
              "application/json": {
                "schema": {
                  "type": "array",
                  "items": {
                    "$ref": "#/components/schemas/FacultyModel"
                  }
                }
              },
              "text/json": {
                "schema": {
                  "type": "array",
                  "items": {
                    "$ref": "#/components/schemas/FacultyModel"
                  }
                }
              }
            }
          },
          "400": {
            "description": "Bad Request"
          },
          "401": {
            "description": "Unauthorized"
          },
          "403": {
            "description": "Forbidden"
          },
          "404": {
            "description": "Not Found"
          },
          "500": {
            "description": "InternalServerError",
            "content": {
              "application/json": {
                "schema": {
                  "$ref": "#/components/schemas/ResponseModel"
                }
              }
            }
          }
        },
        "security": [
          {
            "bearerAuth": []
          }
        ]
      }
    },
    "/api/dictionary/programs": {
      "get": {
        "tags": [
          "dictionary"
        ],
        "summary": "Get a list of active education programs",
        "parameters": [
          {
            "name": "page",
            "in": "query",
            "description": "page number",
            "style": "form",
            "schema": {
              "maximum": 2147483647,
              "minimum": 1,
              "type": "integer",
              "format": "int32",
              "default": 1
            }
          },
          {
            "name": "size",
            "in": "query",
            "description": "required number of elements per page",
            "style": "form",
            "schema": {
              "maximum": 2147483647,
              "minimum": 1,
              "type": "integer",
              "format": "int32",
              "default": 10
            }
          }
        ],
        "responses": {
          "200": {
            "description": "Education programs list retrieved",
            "content": {
              "text/plain": {
                "schema": {
                  "$ref": "#/components/schemas/ProgramPagedListModel"
                }
              },
              "application/json": {
                "schema": {
                  "$ref": "#/components/schemas/ProgramPagedListModel"
                }
              },
              "text/json": {
                "schema": {
                  "$ref": "#/components/schemas/ProgramPagedListModel"
                }
              }
            }
          },
          "400": {
            "description": "Invalid arguments for filtration/pagination"
          },
          "401": {
            "description": "Unauthorized"
          },
          "403": {
            "description": "Forbidden"
          },
          "404": {
            "description": "Not Found"
          },
          "500": {
            "description": "InternalServerError",
            "content": {
              "application/json": {
                "schema": {
                  "$ref": "#/components/schemas/ResponseModel"
                }
              }
            }
          }
        },
        "security": [
          {
            "bearerAuth": []
          }
        ]
      }
    },
    "/document/passport": {
      "post": {
        "tags": [
          "document"
        ],
        "summary": "Add passport (only 1 for person)",
        "operationId": "AddPassport",
        "requestBody": {
          "required": true,
          "content": {
            "application/json": {
              "schema": {
                "$ref": "#/components/schemas/AddPassportRequest"
              }
            }
          }
        },
        "responses": {
          "200": {
            "description": "successful operation",
            "content": {
              "application/json": {
                "schema": {
                  "$ref": "#/components/schemas/AddPassportResponse"
                }
              }
            }
          }
        },
        "security": [
          {
            "bearerAuth": []
          }
        ]
      }
    },
    "/document/passport/{ownerId}": {
      "get": {
        "tags": [
          "document"
        ],
        "summary": "Get user passport by user ID (only for owner, admin and main/assigned manager)",
        "operationId": "GetPassportById",
        "parameters": [
          {
            "name": "ownerId",
            "in": "path",
            "required": true,
            "schema": {
              "type": "string",
              "format": "uuid"
            }
          }
        ],
        "responses": {
          "200": {
            "description": "successful operation",
            "content": {
              "application/json": {
                "schema": {
                  "$ref": "#/components/schemas/GetPassportResponse"
                }
              }
            }
          },
          "401": {
            "description": "Unauthorized"
          },
          "403": {
            "description": "Forbidden"
          },
          "404": {
            "description": "Not Found"
          }
        },
        "security": [
          {
            "bearerAuth": []
          }
        ]
      },
      "patch": {
        "tags": [
          "document"
        ],
        "summary": "Patch user passport by user ID (only for owner, admin and main/assigned manager)",
        "operationId": "PatchPassportById",
        "parameters": [
          {
            "name": "ownerId",
            "in": "path",
            "required": true,
            "schema": {
              "type": "string",
              "format": "uuid"
            }
          }
        ],
        "requestBody": {
          "required": true,
          "content": {
            "application/json": {
              "schema": {
                "$ref": "#/components/schemas/PatchPassportRequest"
              }
            }
          }
        },
        "responses": {
          "200": {
            "description": "successful operation",
            "content": {
              "application/json": {
                "schema": {
                  "$ref": "#/components/schemas/GetPassportResponse"
                }
              }
            }
          }
        },
        "security": [
          {
            "bearerAuth": []
          }
        ]
      }
    },
    "/document/eduDocument": {
      "post": {
        "tags": [
          "document"
        ],
        "summary": "Add education document",
        "operationId": "AddEduDocument",
        "requestBody": {
          "required": true,
          "content": {
            "application/json": {
              "schema": {
                "$ref": "#/components/schemas/AddEduDocumentRequest"
              }
            }
          }
        },
        "responses": {
          "200": {
            "description": "successful operation",
            "content": {
              "application/json": {
                "schema": {
                  "$ref": "#/components/schemas/AddEduDocumentResponse"
                }
              }
            }
          }
        },
        "security": [
          {
            "bearerAuth": []
          }
        ]
      }
    },
    "/document/eduDocument/{eduDocumentId}": {
      "get": {
        "tags": [
          "document"
        ],
        "summary": "Get education document",
        "operationId": "GetEduDocument",
        "parameters": [
          {
            "name": "eduDocumentId",
            "in": "path",
            "required": true,
            "schema": {
              "type": "string",
              "format": "uuid"
            }
          }
        ],
        "responses": {
          "200": {
            "description": "successful operation",
            "content": {
              "application/json": {
                "schema": {
                  "$ref": "#/components/schemas/GetEduDocumentResponse"
                }
              }
            }
          }
        },
        "security": [
          {
            "bearerAuth": []
          }
        ]
      },
      "patch": {
        "tags": [
          "document"
        ],
        "summary": "Get education document",
        "operationId": "PatchEduDocument",
        "parameters": [
          {
            "name": "eduDocumentId",
            "in": "path",
            "required": true,
            "schema": {
              "type": "string",
              "format": "uuid"
            }
          }
        ],
        "requestBody": {
          "required": true,
          "content": {
            "application/json": {
              "schema": {
                "$ref": "#/components/schemas/PatchEduDocumentRequest"
              }
            }
          }
        },
        "responses": {
          "200": {
            "description": "successful operation",
            "content": {
              "application/json": {
                "schema": {
                  "$ref": "#/components/schemas/GetEduDocumentResponse"
                }
              }
            }
          }
        },
        "security": [
          {
            "bearerAuth": []
          }
        ]
      }
    },
    "/document/scan": {
      "post": {
        "tags": [
          "document"
        ],
        "summary": "Add document scan",
        "operationId": "AddScan",
        "requestBody": {
          "required": true,
          "content": {
            "multipart/formdata": {
              "schema": {
                "type": "object",
                "properties": {
                  "file": {
                    "type": "string",
                    "format": "binary"
                  }
                }
              }
            }
          }
        },
        "responses": {
          "200": {
            "description": "successful operation",
            "content": {
              "application/json": {
                "schema": {
                  "type": "object",
                  "properties": {
                    "id": {
                      "type": "string",
                      "format": "uuid"
                    }
                  }
                }
              }
            }
          }
        },
        "security": [
          {
            "bearerAuth": []
          }
        ]
      }
    },
    "/document/scan/{scanId}": {
      "delete": {
        "tags": [
          "document"
        ],
        "summary": "Delete scan by id",
        "operationId": "DeleteScan",
        "parameters": [
          {
            "name": "scanId",
            "in": "path",
            "required": true,
            "schema": {
              "type": "string",
              "format": "uuid"
            }
          }
        ],
        "responses": {
          "200": {
            "description": "successful operation"
          }
        },
        "security": [
          {
            "bearerAuth": []
          }
        ]
      }
    },
    "/notification": {
      "post": {
        "tags": [
          "notification"
        ],
        "summary": "Notification user",
        "operationId": "Notification user",
        "requestBody": {
          "required": true,
          "content": {
            "application/json": {
              "schema": {
                "$ref": "#/components/schemas/NotificationRequest"
              }
            }
          }
        },
        "responses": {
          "200": {
            "description": "successful operation"
          }
        }
      }
    },
    "/user/register": {
      "post": {
        "tags": [
          "user"
        ],
        "summary": "Registration",
        "operationId": "RegisterUser",
        "requestBody": {
          "required": true,
          "content": {
            "application/json": {
              "schema": {
                "$ref": "#/components/schemas/RegisterUserRequest"
              }
            }
          }
        },
        "responses": {
          "200": {
            "description": "successful operation",
            "content": {
              "application/json": {
                "schema": {
                  "$ref": "#/components/schemas/Token"
                }
              }
            }
          }
        }
      }
    },
    "/user/login": {
      "post": {
        "tags": [
          "user"
        ],
        "summary": "Login",
        "operationId": "LoginUser",
        "requestBody": {
          "required": true,
          "content": {
            "application/json": {
              "schema": {
                "$ref": "#/components/schemas/UserCredentials"
              }
            }
          }
        },
        "responses": {
          "200": {
            "description": "successful operation",
            "content": {
              "application/json": {
                "schema": {
                  "$ref": "#/components/schemas/Token"
                }
              }
            }
          }
        }
      }
    },
    "/user/profile": {
      "get": {
        "tags": [
          "user"
        ],
        "summary": "Get your profile",
        "operationId": "GetUser",
        "responses": {
          "200": {
            "description": "successful operation",
            "content": {
              "application/json": {
                "schema": {
                  "$ref": "#/components/schemas/UserResponse"
                }
              }
            }
          },
          "401": {
            "description": "Unauthorized"
          },
          "404": {
            "description": "Not Found"
          }
        },
        "security": [
          {
            "bearerAuth": []
          }
        ]
      },
      "patch": {
        "tags": [
          "user"
        ],
        "summary": "Patch your profile",
        "operationId": "PatchUser",
        "requestBody": {
          "required": true,
          "content": {
            "application/json": {
              "schema": {
                "$ref": "#/components/schemas/PatchUserRequest"
              }
            }
          }
        },
        "responses": {
          "200": {
            "description": "successful operation",
            "content": {
              "application/json": {
                "schema": {
                  "$ref": "#/components/schemas/UserResponse"
                }
              }
            }
          }
        },
        "security": [
          {
            "bearerAuth": []
          }
        ]
      }
    },
    "/user/profile/changePassword": {
      "patch": {
        "tags": [
          "user"
        ],
        "summary": "Change your password",
        "operationId": "changePassword",
        "requestBody": {
          "required": true,
          "content": {
            "application/json": {
              "schema": {
                "$ref": "#/components/schemas/ChangePasswordRequest"
              }
            }
          }
        },
        "responses": {
          "200": {
            "description": "successful operation"
          }
        },
        "security": [
          {
            "bearerAuth": []
          }
        ]
      }
    },
    "/user/{userId}": {
      "get": {
        "tags": [
          "user"
        ],
        "summary": "Get user profile by ID (only for admin and main/assigned manager)",
        "operationId": "GetUserById",
        "parameters": [
          {
            "name": "userId",
            "in": "path",
            "required": true,
            "schema": {
              "type": "string",
              "format": "uuid"
            }
          }
        ],
        "responses": {
          "200": {
            "description": "successful operation",
            "content": {
              "application/json": {
                "schema": {
                  "$ref": "#/components/schemas/UserResponse"
                }
              }
            }
          },
          "401": {
            "description": "Unauthorized"
          },
          "403": {
            "description": "Forbidden"
          },
          "404": {
            "description": "Not Found"
          }
        },
        "security": [
          {
            "bearerAuth": []
          }
        ]
      },
      "patch": {
        "tags": [
          "user"
        ],
        "summary": "Patch user profile by ID (only for admin and main/assigned manager)",
        "operationId": "PatchUserById",
        "parameters": [
          {
            "name": "userId",
            "in": "path",
            "required": true,
            "schema": {
              "type": "string",
              "format": "uuid"
            }
          }
        ],
        "requestBody": {
          "required": true,
          "content": {
            "application/json": {
              "schema": {
                "$ref": "#/components/schemas/PatchUserRequest"
              }
            }
          }
        },
        "responses": {
          "200": {
            "description": "successful operation",
            "content": {
              "application/json": {
                "schema": {
                  "$ref": "#/components/schemas/UserResponse"
                }
              }
            }
          }
        },
        "security": [
          {
            "bearerAuth": []
          }
        ]
      }
    },
    "/applicant/register": {
      "post": {
        "tags": [
          "applicant"
        ],
        "summary": "Registration",
        "operationId": "RegisterApplicant",
        "requestBody": {
          "required": true,
          "content": {
            "application/json": {
              "schema": {
                "$ref": "#/components/schemas/RegisterApplicantRequest"
              }
            }
          }
        },
        "responses": {
          "200": {
            "description": "successful operation",
            "content": {
              "application/json": {
                "schema": {
                  "$ref": "#/components/schemas/Token"
                }
              }
            }
          }
        }
      }
    },
    "/applicant/profile": {
      "get": {
        "tags": [
          "applicant"
        ],
        "summary": "Get your profile",
        "operationId": "GetApplicant",
        "responses": {
          "200": {
            "description": "successful operation",
            "content": {
              "application/json": {
                "schema": {
                  "$ref": "#/components/schemas/ApplicantResponse"
                }
              }
            }
          },
          "401": {
            "description": "Unauthorized"
          },
          "404": {
            "description": "Not Found"
          }
        },
        "security": [
          {
            "bearerAuth": []
          }
        ]
      },
      "patch": {
        "tags": [
          "applicant"
        ],
        "summary": "Patch your profile",
        "operationId": "PatchApplicant",
        "requestBody": {
          "required": true,
          "content": {
            "application/json": {
              "schema": {
                "$ref": "#/components/schemas/PatchApplicantRequest"
              }
            }
          }
        },
        "responses": {
          "200": {
            "description": "successful operation",
            "content": {
              "application/json": {
                "schema": {
                  "$ref": "#/components/schemas/ApplicantResponse"
                }
              }
            }
          }
        },
        "security": [
          {
            "bearerAuth": []
          }
        ]
      }
    },
    "/applicant/application": {
      "post": {
        "tags": [
          "applicant"
        ],
        "summary": "Post application",
        "operationId": "PostApplication",
        "requestBody": {
          "required": true,
          "content": {
            "application/json": {
              "schema": {
                "$ref": "#/components/schemas/PostApplicationRequest"
              }
            }
          }
        },
        "responses": {
          "200": {
            "description": "successful operation",
            "content": {
              "application/json": {
                "schema": {
                  "$ref": "#/components/schemas/ApplicationResponse"
                }
              }
            }
          }
        }
      }
    },
    "/applicant/{applicantId}": {
      "get": {
        "tags": [
          "applicant"
        ],
        "summary": "Get applicant profile by ID (only for admin and main/assigned manager)",
        "operationId": "GetApplicantById",
        "parameters": [
          {
            "name": "applicantId",
            "in": "path",
            "required": true,
            "schema": {
              "type": "string",
              "format": "uuid"
            }
          }
        ],
        "responses": {
          "200": {
            "description": "successful operation",
            "content": {
              "application/json": {
                "schema": {
                  "$ref": "#/components/schemas/ApplicantResponse"
                }
              }
            }
          },
          "401": {
            "description": "Unauthorized"
          },
          "403": {
            "description": "Forbidden"
          },
          "404": {
            "description": "Not Found"
          }
        },
        "security": [
          {
            "bearerAuth": []
          }
        ]
      },
      "patch": {
        "tags": [
          "applicant"
        ],
        "summary": "Patch applicant profile by ID (only for admin and main/assigned manager)",
        "operationId": "PatchApplicantById",
        "parameters": [
          {
            "name": "applicantId",
            "in": "path",
            "required": true,
            "schema": {
              "type": "string",
              "format": "uuid"
            }
          }
        ],
        "requestBody": {
          "required": true,
          "content": {
            "application/json": {
              "schema": {
                "$ref": "#/components/schemas/PatchApplicantRequest"
              }
            }
          }
        },
        "responses": {
          "200": {
            "description": "successful operation",
            "content": {
              "application/json": {
                "schema": {
                  "$ref": "#/components/schemas/ApplicantResponse"
                }
              }
            }
          }
        },
        "security": [
          {
            "bearerAuth": []
          }
        ]
      }
    }
  },
  "components": {
    "schemas": {
      "EducationDocumentTypeModel": {
        "required": [
          "createTime",
          "educationLevel",
          "id",
          "name"
        ],
        "type": "object",
        "properties": {
          "id": {
            "type": "string",
            "format": "uuid"
          },
          "createTime": {
            "type": "string",
            "format": "date-time"
          },
          "name": {
            "minLength": 1,
            "type": "string"
          },
          "educationLevel": {
            "$ref": "#/components/schemas/EducationLevelModel"
          },
          "nextEducationLevels": {
            "type": "array",
            "items": {
              "$ref": "#/components/schemas/EducationLevelModel"
            },
            "nullable": true
          }
        },
        "additionalProperties": false
      },
      "EducationLevelModel": {
        "required": [
          "id",
          "name"
        ],
        "type": "object",
        "properties": {
          "id": {
            "type": "integer",
            "format": "int32"
          },
          "name": {
            "minLength": 1,
            "type": "string"
          }
        },
        "additionalProperties": false
      },
      "EducationProgramModel": {
        "required": [
          "createTime",
          "educationForm",
          "educationLevel",
          "faculty",
          "id",
          "language",
          "name"
        ],
        "type": "object",
        "properties": {
          "id": {
            "type": "string",
            "format": "uuid"
          },
          "createTime": {
            "type": "string",
            "format": "date-time"
          },
          "name": {
            "minLength": 1,
            "type": "string"
          },
          "code": {
            "type": "string",
            "nullable": true
          },
          "language": {
            "minLength": 1,
            "type": "string"
          },
          "educationForm": {
            "minLength": 1,
            "type": "string"
          },
          "faculty": {
            "$ref": "#/components/schemas/FacultyModel"
          },
          "educationLevel": {
            "$ref": "#/components/schemas/EducationLevelModel"
          }
        },
        "additionalProperties": false
      },
      "FacultyModel": {
        "required": [
          "createTime",
          "id",
          "name"
        ],
        "type": "object",
        "properties": {
          "id": {
            "type": "string",
            "format": "uuid"
          },
          "createTime": {
            "type": "string",
            "format": "date-time"
          },
          "name": {
            "minLength": 1,
            "type": "string"
          }
        },
        "additionalProperties": false
      },
      "PageInfoModel": {
        "type": "object",
        "properties": {
          "size": {
            "type": "integer",
            "format": "int32"
          },
          "count": {
            "type": "integer",
            "format": "int32"
          },
          "current": {
            "type": "integer",
            "format": "int32"
          }
        },
        "additionalProperties": false
      },
      "ProgramPagedListModel": {
        "type": "object",
        "properties": {
          "programs": {
            "type": "array",
            "items": {
              "$ref": "#/components/schemas/EducationProgramModel"
            },
            "nullable": true
          },
          "pagination": {
            "$ref": "#/components/schemas/PageInfoModel"
          }
        },
        "additionalProperties": false
      },
      "ResponseModel": {
        "type": "object",
        "properties": {
          "status": {
            "type": "string",
            "nullable": true
          },
          "message": {
            "type": "string",
            "nullable": true
          }
        },
        "additionalProperties": false
      },
      "PatchPassportRequest": {
        "type": "object",
        "properties": {
          "series": {
            "type": "string"
          },
          "birthPlace": {
            "type": "string"
          },
          "issueDate": {
            "type": "string",
            "format": "date-time"
          },
          "issuePerson": {
            "type": "string"
          }
        }
      },
      "GetPassportResponse": {
        "type": "object",
        "required": [
          "id",
          "ownerId",
          "series",
          "birthPlace",
          "issueDate",
          "issuePerson"
        ],
        "properties": {
          "id": {
            "type": "string",
            "format": "uuid"
          },
          "ownerId": {
            "type": "string",
            "format": "uuid"
          },
          "series": {
            "type": "string"
          },
          "birthPlace": {
            "type": "string"
          },
          "issueDate": {
            "type": "string",
            "format": "date-time"
          },
          "issuePerson": {
            "type": "string"
          }
        }
      },
      "AddPassportResponse": {
        "type": "object",
        "required": [
          "id"
        ],
        "properties": {
          "id": {
            "type": "string",
            "format": "uuid"
          }
        }
      },
      "AddPassportRequest": {
        "type": "object",
        "required": [
          "series",
          "birthPlace",
          "issueDate",
          "issuePerson"
        ],
        "properties": {
          "series": {
            "type": "string"
          },
          "birthPlace": {
            "type": "string"
          },
          "issueDate": {
            "type": "string",
            "format": "date-time"
          },
          "issuePerson": {
            "type": "string"
          }
        }
      },
      "RegisterUserRequest": {
        "type": "object",
        "required": [
          "username",
          "email",
          "password"
        ],
        "properties": {
          "username": {
            "type": "string"
          },
          "email": {
            "type": "string"
          },
          "password": {
            "type": "string"
          }
        }
      },
      "UserCredentials": {
        "type": "object",
        "required": [
          "email",
          "password"
        ],
        "properties": {
          "email": {
            "type": "string"
          },
          "password": {
            "type": "string"
          }
        }
      },
      "Token": {
        "type": "object",
        "required": [
          "token"
        ],
        "properties": {
          "token": {
            "type": "string"
          }
        }
      },
      "PatchUserRequest": {
        "type": "object",
        "properties": {
          "username": {
            "type": "string"
          },
          "email": {
            "type": "string"
          }
        }
      },
      "ChangePasswordRequest": {
        "type": "object",
        "required": [
          "oldPassword",
          "newPassword"
        ],
        "properties": {
          "oldPassword": {
            "type": "string"
          },
          "newPassword": {
            "type": "string"
          }
        }
      },
      "UserResponse": {
        "type": "object",
        "required": [
          "id",
          "username",
          "email"
        ],
        "properties": {
          "id": {
            "type": "string",
            "format": "uuid"
          },
          "username": {
            "type": "string"
          },
          "email": {
            "type": "string"
          }
        }
      },
      "RegisterApplicantRequest": {
        "type": "object",
        "required": [
          "username",
          "email",
          "password"
        ],
        "properties": {
          "username": {
            "type": "string"
          },
          "email": {
            "type": "string"
          },
          "password": {
            "type": "string"
          },
          "birthDate": {
            "type": "string",
            "format": "date-time"
          },
          "gender": {
            "$ref": "#/components/schemas/Gender"
          },
          "citizenship": {
            "type": "string"
          },
          "phoneNumber": {
            "type": "string"
          }
        }
      },
      "ApplicantResponse": {
        "type": "object",
        "required": [
          "id",
          "username",
          "email"
        ],
        "properties": {
          "id": {
            "type": "string",
            "format": "uuid"
          },
          "username": {
            "type": "string"
          },
          "email": {
            "type": "string"
          },
          "birthDate": {
            "type": "string",
            "format": "date-time"
          },
          "gender": {
            "$ref": "#/components/schemas/Gender"
          },
          "citizenship": {
            "type": "string"
          },
          "phoneNumber": {
            "type": "string"
          }
        }
      },
      "PatchApplicantRequest": {
        "type": "object",
        "properties": {
          "username": {
            "type": "string"
          },
          "email": {
            "type": "string"
          },
          "birthDate": {
            "type": "string",
            "format": "date-time"
          },
          "gender": {
            "$ref": "#/components/schemas/Gender"
          },
          "citizenship": {
            "type": "string"
          },
          "phoneNumber": {
            "type": "string"
          }
        }
      },
      "AddEduDocumentRequest": {
        "type": "object",
        "required": [
          "name",
          "typeId"
        ],
        "properties": {
          "userId": {
            "type": "string",
            "format": "uuid"
          },
          "name": {
            "type": "string"
          },
          "typeId": {
            "type": "string",
            "format": "uuid"
          }
        }
      },
      "AddEduDocumentResponse": {
        "type": "object",
        "required": [
          "id"
        ],
        "properties": {
          "id": {
            "type": "string",
            "format": "uuid"
          }
        }
      },
      "GetEduDocumentResponse": {
        "type": "object",
        "required": [
          "id",
          "name",
          "typeId",
          "ownerId"
        ],
        "properties": {
          "id": {
            "type": "string",
            "format": "uuid"
          },
          "name": {
            "type": "string"
          },
          "typeId": {
            "type": "string",
            "format": "uuid"
          },
          "ownerId": {
            "type": "string",
            "format": "uuid"
          }
        }
      },
      "PatchEduDocumentRequest": {
        "type": "object",
        "properties": {
          "name": {
            "type": "string"
          },
          "typeId": {
            "type": "string",
            "format": "uuid"
          }
        }
      },
      "NotificationRequest": {
        "type": "object",
        "properties": {
          "email": {
            "type": "string"
          },
          "message": {
            "type": "string"
          }
        }
      },
      "PostApplicationRequest": {
        "type": "object",
        "properties": {
          "programId": {
            "type": "string",
            "format": "uuid"
          }
        }
      },
      "ApplicationResponse": {
        "type": "object",
        "properties": {
          "programId": {
            "type": "string",
            "format": "uuid"
          },
          "status": {
            "$ref": "#/components/schemas/ApplicationStatus"
          },
          "assignedManagerId": {
            "type": "string",
            "format": "uuid"
          }
        }
      },
      "Gender": {
        "type": "string",
        "enum": [
          "Male",
          "Female"
        ]
      },
      "ApplicationStatus": {
        "type": "string",
        "enum": [
          "Created",
          "Pending",
          "Approved",
          "Rejected",
          "Closed"
        ]
      }
    },
    "securitySchemes": {
      "bearerAuth": {
        "type": "http",
        "scheme": "bearer",
        "bearerFormat": "JWT"
      }
    }
  }
}